image_keras/__init__.py
image_keras/batch_transform.py
image_keras/flow_directory.py
image_keras/inout_generator.py
image_keras/model_io.py
image_keras/model_manager.py
image_keras/keras/__init__.py
image_keras/keras/callbacks/__init__.py
image_keras/keras/callbacks/callbacks_after_epoch.py
image_keras/keras/layers/__init__.py
image_keras/keras/layers/extract_patch_layer.py
image_keras/keras/losses/__init__.py
image_keras/keras/metrics/__init__.py
image_keras/supports/__init__.py
image_keras/supports/file.py
image_keras/supports/folder.py
image_keras/supports/generator.py
image_keras/supports/list.py
image_keras/supports/map.py
image_keras/supports/optional.py
image_keras/supports/path.py
image_keras/supports/sftp.py
image_keras/supports/tuple_op.py
image_keras/supports/dl/__init__.py
image_keras/supports/dl/report.py
image_keras/supports/dl/report_slack.py
image_keras/supports/functional/__init__.py
image_keras/supports/functional/either.py
image_keras/supports/functional/future.py
image_keras/supports/functional/monad.py
image_keras/supports/functional/option.py
image_keras/tf/__init__.py
image_keras/tf/keras/__init__.py
image_keras/tf/keras/layers/__init__.py
image_keras/tf/keras/layers/extract_patch_layer.py
image_keras/tf/keras/losses/__init__.py
image_keras/tf/keras/losses/losses_binary_boundary_crossentropy.py
image_keras/tf/keras/losses/losses_focal_loss.py
image_keras/tf/keras/metrics/__init__.py
image_keras/tf/keras/metrics/binary_class_mean_iou.py
image_keras/tf/utils/__init__.py
image_keras/tf/utils/gc_storage.py
image_keras/tf/utils/gc_tpu.py
image_keras/tf/utils/gpu_check.py
image_keras/tf/utils/images.py
image_keras/tf/utils/model.py
image_keras/utils/__init__.py
image_keras/utils/image_color_transform.py
image_keras/utils/image_info.py
image_keras/utils/image_io.py
image_keras/utils/image_slice.py
image_keras/utils/image_transform.py
image_keras-0.3.5.dist-info/LICENSE
image_keras-0.3.5.dist-info/METADATA
image_keras-0.3.5.dist-info/WHEEL
image_keras-0.3.5.dist-info/top_level.txt
image_keras-0.3.5.dist-info/RECORD
