Metadata-Version: 2.1
Name: image-keras
Version: 0.3.5
Summary: The fundamental package needed for common purpose with Python.
Home-page: https://github.com/tenkeyless/image-keras
Author: TenKeyLess
Author-email: blivme84@naver.com
License: MIT
Keywords: common util
Platform: UNKNOWN
Classifier: Intended Audience :: Developers
Classifier: Programming Language :: Python :: 3.7
Classifier: License :: OSI Approved :: MIT License
Classifier: Operating System :: MacOS
Classifier: Operating System :: Unix
Requires-Python: >=3.7
Requires-Dist: toolz (>=0.10.0)
Requires-Dist: Keras (>=2.4.0)
Requires-Dist: tensorflow (>=2.3.1)
